bigdl/__init__.py
bigdl/serving/client.py
bigdl/serving/env.py
bigdl/serving/log4Error.py
bigdl/serving/schema.py
bigdl/serving/kafka/client.py
bigdl/serving/kafka/kafka_example.py
bigdl/share/serving/cluster-serving-py-setup.py
bigdl/share/serving/perf-benchmark/e2e_throughput.py
bigdl_serving-2.4.0.data/scripts/cluster-serving-init
bigdl_serving-2.4.0.data/scripts/cluster-serving-py-setup.py
bigdl_serving-2.4.0.data/scripts/cluster-serving-shutdown
bigdl_serving-2.4.0.data/scripts/cluster-serving-start
bigdl_serving-2.4.0.data/scripts/cluster-with-numactl.sh
bigdl_serving-2.4.0.data/scripts/config.yaml
bigdl_serving-2.4.0.data/scripts/download-serving-jar.sh
bigdl_serving-2.4.0.dist-info/METADATA
bigdl_serving-2.4.0.dist-info/WHEEL
bigdl_serving-2.4.0.dist-info/top_level.txt
bigdl_serving-2.4.0.dist-info/RECORD
